{
  "solutions": [
    { "id": 1, "word": "hello" },
    { "id": 2, "word": "apple" },
    { "id": 3, "word": "spade" },
    { "id": 4, "word": "drive" },
    { "id": 5, "word": "train" },
    { "id": 6, "word": "ninja" },
    { "id": 7, "word": "drain" },
    { "id": 8, "word": "funny" },
    { "id": 9, "word": "title" },
    { "id": 10, "word": "blink" },
    { "id": 11, "word": "react" },
    { "id": 12, "word": "redux" },
    { "id": 13, "word": "comic" },
    { "id": 14, "word": "gamer" },
    { "id": 15, "word": "grain" }
  ]
}
